LICENSE
MANIFEST.in
README.rst
setup.py
django_basic_stats.egg-info/PKG-INFO
django_basic_stats.egg-info/SOURCES.txt
django_basic_stats.egg-info/dependency_links.txt
django_basic_stats.egg-info/requires.txt
django_basic_stats.egg-info/top_level.txt
stats/__init__.py
stats/admin.py
stats/middleware.py
stats/models.py
stats/urls.py
stats/views.py
stats/migrations/0001_initial.py
stats/migrations/__init__.py
stats/templates/stats/entries.html
stats/templates/stats/google.html
stats/templates/stats/home.html
stats/templates/stats/mobile_report.html
stats/templates/stats/referers.html
stats/templates/stats/partials/sidebar.html