Metadata-Version: 1.0
Name: django-basic-stats
Version: 0.2.0
Summary: django-basic-stats is a simple traffic statistics application. It show latest referrer, google queried terms or overall hits count. It also provides optional logging and statistics for mobile devices.
Home-page: UNKNOWN
Author: Piotr Malinski
Author-email: riklaunim@gmail.com
License: UNKNOWN
Platform: UNKNOWN
